sysexit/__init__.py
sysexit-0.1.1.dist-info/METADATA
sysexit-0.1.1.dist-info/WHEEL
sysexit-0.1.1.dist-info/top_level.txt
sysexit-0.1.1.dist-info/RECORD
