Metadata-Version: 2.1
Name: sysexit
Version: 0.1.1
Summary: Immediately stops execution when imported by raising a SystemExit exception
Author-email: Wendelin Wemhöner <wendelin.wemhoener@gmail.com>
Classifier: Programming Language :: Python :: 3
Classifier: Operating System :: OS Independent
Requires-Python: >=3.6
